mcp_this_openapi/__init__.py
mcp_this_openapi/__main__.py
mcp_this_openapi/server.py
mcp_this_openapi/config/__init__.py
mcp_this_openapi/config/loader.py
mcp_this_openapi/config/models.py
mcp_this_openapi/openapi/__init__.py
mcp_this_openapi/openapi/auth.py
mcp_this_openapi/openapi/fetcher.py
mcp_this_openapi/openapi/filter.py
mcp_this_openapi/openapi/schema_fix.py
mcp_this_openapi/openapi/tool_naming.py
mcp_this_openapi/openapi/url_utils.py
mcp_this_openapi-0.0.10.dist-info/METADATA
mcp_this_openapi-0.0.10.dist-info/WHEEL
mcp_this_openapi-0.0.10.dist-info/entry_points.txt
mcp_this_openapi-0.0.10.dist-info/licenses/LICENSE
mcp_this_openapi-0.0.10.dist-info/RECORD
