Metadata-Version: 2.4
Name: mcp-this-openapi
Version: 0.0.10
Summary: MCP Server that creates tools from OpenAPI/Swagger specifications
Author-email: Shane Kercheval <shane.kercheval@gmail.com>
License-File: LICENSE
Keywords: AI,Claude,MCP,OpenAPI,Swagger,tools
Requires-Python: >=3.11
Requires-Dist: fastmcp>=2.10.4
Requires-Dist: httpx>=0.28.1
Requires-Dist: mcp>=1.11.0
Requires-Dist: pydantic>=2.11.7
Requires-Dist: pyyaml>=6.0.2
